pycourselet/__init__.py
pycourselet/courselet_context_compiler.py
pycourselet/courselet_scanner.py
pycourselet/cmd/__init__.py
pycourselet/cmd/courselet.py
pycourselet/contexts/__init__.py
pycourselet/contexts/audio_context.py
pycourselet/contexts/block_context.py
pycourselet/contexts/checkbox_context.py
pycourselet/contexts/context.py
pycourselet/contexts/context_manager.py
pycourselet/contexts/control_contexts.py
pycourselet/contexts/element_context.py
pycourselet/contexts/enumerate_context.py
pycourselet/contexts/heading_context.py
pycourselet/contexts/image_context.py
pycourselet/contexts/list_context.py
pycourselet/contexts/math_context.py
pycourselet/contexts/page_context.py
pycourselet/contexts/paragraph_context.py
pycourselet/contexts/table_contexts.py
pycourselet/contexts/text_context.py
pycourselet/tokens/__init__.py
pycourselet/tokens/control_tokens.py
pycourselet/tokens/enumerate_token.py
pycourselet/tokens/header_token.py
pycourselet/tokens/image_token.py
pycourselet/tokens/list_token.py
pycourselet/tokens/table_tokens.py
pycourselet/tokens/text_tokens.py
pycourselet/tokens/token.py
pycourselet-0.2.7.dist-info/LICENSE
pycourselet-0.2.7.dist-info/METADATA
pycourselet-0.2.7.dist-info/WHEEL
pycourselet-0.2.7.dist-info/entry_points.txt
pycourselet-0.2.7.dist-info/top_level.txt
pycourselet-0.2.7.dist-info/RECORD
