Metadata-Version: 2.1
Name: pycourselet
Version: 0.2.7
Summary: Tool to create courselets for Lernsax
Home-page: https://github.com/CsharpLassi/pycourselet
Author: Christoph Laßmann
Author-email: csharplassi@posteo.de
License: UNKNOWN
Platform: UNKNOWN
Classifier: Programming Language :: Python :: 3
Classifier: License :: OSI Approved :: GNU General Public License v3 (GPLv3)
Classifier: Operating System :: OS Independent
Requires-Python: >=3.7
License-File: LICENSE
Requires-Dist: wget (==3.2)
Requires-Dist: cairosvg (==2.5.0)
Requires-Dist: jinja2 (==2.11.2)
